clearmap_nmr.libs/libgomp-a34b3233.so.1.0.0
ClearMap/Settings.py
ClearMap/Environment.py
ClearMap/Compile.py
ClearMap/__init__.py
ClearMap/Alignment/Resampling.py
ClearMap/Alignment/Elastix.py
ClearMap/Alignment/Annotation.py
ClearMap/Alignment/Elastix_GF.py
ClearMap/Alignment/__init__.py
ClearMap/Alignment/Stitching/StitchingRigid.py
ClearMap/Alignment/Stitching/Tracking.py
ClearMap/Alignment/Stitching/StitchingWobbly.py
ClearMap/Alignment/Stitching/__init__.py
ClearMap/Alignment/Stitching/_Todo/StitchingTera.py
ClearMap/Alignment/Stitching/_Todo/StitchingRigid.py
ClearMap/Scripts/CellMap.py
ClearMap/Scripts/TubeMap.py
ClearMap/Scripts/CellMap_zl_20221117.py
ClearMap/Scripts/CellMap_zl_20221116.py
ClearMap/Scripts/__init__.py
ClearMap/Visualization/Plot3d.py
ClearMap/Visualization/__init__.py
ClearMap/Visualization/Color.py
ClearMap/Visualization/Mesh/IcoSphere.py
ClearMap/Visualization/Mesh/__init__.py
ClearMap/Visualization/Qt/Utils.py
ClearMap/Visualization/Qt/DataViewer.py
ClearMap/Visualization/Qt/Plot3d.py
ClearMap/Visualization/Qt/__init__.py
ClearMap/Visualization/Qt/_Todo/ImageItem.py
ClearMap/Visualization/Qt/_Todo/GUI/PipelineViewer.py
ClearMap/Visualization/Qt/_Todo/GUI/ParameterItems.py
ClearMap/Visualization/Qt/_Todo/GUI/FileDialog.py
ClearMap/Visualization/Qt/_Todo/GUI/Parameter.py
ClearMap/Visualization/Qt/_Todo/GUI/ImageProcessing.py
ClearMap/Visualization/Qt/_Todo/GUI/DataViewerSimple.py
ClearMap/Visualization/Qt/_Todo/GUI/GUI.py
ClearMap/Visualization/Qt/_Todo/GUI/__init__.py
ClearMap/Visualization/Matplotlib/PlotUtils.py
ClearMap/Visualization/Matplotlib/__init__.py
ClearMap/Visualization/Vispy/PlotGraph3d.py
ClearMap/Visualization/Vispy/VolumeVisual.py
ClearMap/Visualization/Vispy/Plot3d.py
ClearMap/Visualization/Vispy/__init__.py
ClearMap/Visualization/Vispy/GraphVisual.py
ClearMap/Visualization/Vispy/TurntableCamera.py
ClearMap/Visualization/_Todo/plot_utils.py
clearmap_nmr-0.3.0.dist-info/LICENSE
clearmap_nmr-0.3.0.dist-info/WHEEL
clearmap_nmr-0.3.0.dist-info/top_level.txt
clearmap_nmr-0.3.0.dist-info/LICENSE.txt
clearmap_nmr-0.3.0.dist-info/METADATA
clearmap_nmr-0.3.0.dist-info/RECORD
