Metadata-Version: 2.2
Name: clearmap-nmr
Version: 0.3.0
Summary: A package for ClearMap project
Author: Christoph Kirst, Georgi Fenton
Maintainer: Omar Valerio, Max Planck Institute of Neurobiology
License: GPL-3.0
Project-URL: Homepage, https://github.com/mpinb/clearmap-nmr
Project-URL: Repository, https://github.com/mpinb/clearmap-nmr
Project-URL: Bug Tracker, https://github.com/mpinb/clearmap-nmr/issues
Project-URL: Documentation, https://github.com/mpinb/clearmap-nmr
Keywords: image-processing,neuroscience,clearmap,microscopy
Classifier: Development Status :: 3 - Alpha
Classifier: Intended Audience :: Science/Research
Classifier: License :: OSI Approved :: GNU General Public License v3 (GPLv3)
Classifier: Programming Language :: Python :: 3
Classifier: Programming Language :: Python :: 3.8
Classifier: Programming Language :: Python :: 3.9
Classifier: Programming Language :: Python :: 3.10
Classifier: Programming Language :: Python :: 3.11
Classifier: Programming Language :: Cython
Classifier: Topic :: Scientific/Engineering :: Image Processing
Classifier: Topic :: Scientific/Engineering :: Bio-Informatics
Requires-Python: >=3.8
License-File: LICENSE
License-File: LICENSE.txt
Requires-Dist: numpy>=1.19
Provides-Extra: docs
Requires-Dist: sphinx; extra == "docs"
Requires-Dist: sphinx-rtd-theme; extra == "docs"
